{
  "version": 1,
  "canisters": {
    "connectd": {
      "main": "src/connectd/main.mo"
    },
    "linkedup": {
      "dependencies": [
        "connectd"
      ],
      "main": "src/linkedup/main.mo"
    },
    "linkedup_assets": {
      "dependencies": [
        "linkedup"
      ],
      "frontend": {
        "entrypoint": "src/linkedup/public/main.js"
      },
      "type": "assets",
      "source": [
        "src/linkedup/public",
        "dist/linkedup_assets"
      ]
    },
    "asset_storage": {
      "dependencies": [
        "linkedup"
      ],
      "type": "custom",
      "candid": "src/asset_storage_rs/asset_storage.did",
      "wasm": "target/wasm32-unknown-unknown/debug/asset_storage_rs.wasm",
      "build": "cargo build --target wasm32-unknown-unknown --package asset_storage_rs"
    },
    "asset_storage_assets": {
      "dependencies": [
        "asset_storage"
      ],
      "frontend": {
        "entrypoint": "src/asset_storage_assets/public/index.jsx"
      },
      "source": [
        "src/asset_storage_assets/assets",
        "dist/asset_storage_assets/"
      ],
      "type": "assets"
    },
    "bigmap": {
      "type": "custom",
      "candid": "vendor/bigmap-rs/src/bigmap_index.did",
      "wasm": "vendor/bigmap-rs/target/wasm32-unknown-unknown/release/bigmap_index.wasm",
      "build": "./vendor/bigmap-rs/build"
    },
    "bigmap_data": {
      "type": "custom",
      "candid": "vendor/bigmap-rs/src/bigmap_data.did",
      "wasm": "vendor/bigmap-rs/target/wasm32-unknown-unknown/release/bigmap_data.wasm",
      "build": "./vendor/bigmap-rs/build"
    }
  },
  "defaults": {
    "build": {
      "packtool": ""
    }
  },
  "dfx": "0.6.14",
  "networks": {
    "ic": {
      "providers": [
        "https://gw.dfinity.network"
      ],
      "type": "persistent"
    },
    "local": {
      "bind": "127.0.0.1:8000",
      "type": "ephemeral"
    }
  }
}